MANIFEST.in
setup.py
docs/HISTORY.txt
src/dolmen/__init__.py
src/dolmen.widget.tinymce.egg-info/PKG-INFO
src/dolmen.widget.tinymce.egg-info/SOURCES.txt
src/dolmen.widget.tinymce.egg-info/dependency_links.txt
src/dolmen.widget.tinymce.egg-info/entry_points.txt
src/dolmen.widget.tinymce.egg-info/namespace_packages.txt
src/dolmen.widget.tinymce.egg-info/not-zip-safe
src/dolmen.widget.tinymce.egg-info/requires.txt
src/dolmen.widget.tinymce.egg-info/top_level.txt
src/dolmen/widget/__init__.py
src/dolmen/widget/tinymce/README.txt
src/dolmen/widget/tinymce/__init__.py
src/dolmen/widget/tinymce/configure.zcml
src/dolmen/widget/tinymce/ftesting.zcml
src/dolmen/widget/tinymce/library.py
src/dolmen/widget/tinymce/tests.py
src/dolmen/widget/tinymce/widget.py
src/dolmen/widget/tinymce/resources/jquery_tiny_mce.js
src/dolmen/widget/tinymce/templates/display.pt
src/dolmen/widget/tinymce/templates/input.pt