Metadata-Version: 1.0
Name: dolmen.widget.tinymce
Version: 1.0b3
Summary: A rich text widget using TinyMCE for Dolmen
Home-page: http://gitweb.dolmen-project.org/
Author: Souheil Chelfouh
Author-email: trollfot@gmail.com
License: GPL
Keywords: Grok Zope3 CMS Dolmen
Platform: UNKNOWN
Classifier: Development Status :: 4 - Beta
Classifier: Environment :: Web Environment
Classifier: Framework :: Zope3
Classifier: Intended Audience :: Other Audience
Classifier: License :: OSI Approved :: GNU General Public License (GPL)
Classifier: Operating System :: OS Independent
Classifier: Programming Language :: Python
